aucampia/__init__.py
aucampia/rdflib_xtl/__init__.py
aucampia/rdflib_xtl/_version.py
aucampia/rdflib_xtl/cli.py
aucampia/rdflib_xtl/py.typed
aucampia.rdflib_xtl-0.6.0.dist-info/entry_points.txt
aucampia.rdflib_xtl-0.6.0.dist-info/WHEEL
aucampia.rdflib_xtl-0.6.0.dist-info/METADATA
aucampia.rdflib_xtl-0.6.0.dist-info/RECORD
